poetry/__init__.py
poetry/__main__.py
poetry/__version__.py
poetry/_vendor/.gitignore
poetry/config/__init__.py
poetry/config/config.py
poetry/config/config_source.py
poetry/config/dict_config_source.py
poetry/config/file_config_source.py
poetry/console/__init__.py
poetry/console/application.py
poetry/console/args/__init__.py
poetry/console/args/run_args_parser.py
poetry/console/commands/__init__.py
poetry/console/commands/about.py
poetry/console/commands/add.py
poetry/console/commands/build.py
poetry/console/commands/cache/__init__.py
poetry/console/commands/cache/cache.py
poetry/console/commands/cache/clear.py
poetry/console/commands/cache/list.py
poetry/console/commands/check.py
poetry/console/commands/command.py
poetry/console/commands/config.py
poetry/console/commands/debug/__init__.py
poetry/console/commands/debug/debug.py
poetry/console/commands/debug/info.py
poetry/console/commands/debug/resolve.py
poetry/console/commands/env/__init__.py
poetry/console/commands/env/env.py
poetry/console/commands/env/info.py
poetry/console/commands/env/list.py
poetry/console/commands/env/remove.py
poetry/console/commands/env/use.py
poetry/console/commands/env_command.py
poetry/console/commands/export.py
poetry/console/commands/init.py
poetry/console/commands/install.py
poetry/console/commands/installer_command.py
poetry/console/commands/lock.py
poetry/console/commands/new.py
poetry/console/commands/publish.py
poetry/console/commands/remove.py
poetry/console/commands/run.py
poetry/console/commands/search.py
poetry/console/commands/self/__init__.py
poetry/console/commands/self/self.py
poetry/console/commands/self/update.py
poetry/console/commands/shell.py
poetry/console/commands/show.py
poetry/console/commands/update.py
poetry/console/commands/version.py
poetry/console/config/__init__.py
poetry/console/config/application_config.py
poetry/console/logging/__init__.py
poetry/console/logging/formatters/__init__.py
poetry/console/logging/formatters/builder_formatter.py
poetry_windows_fix-1.1.11.dist-info/entry_points.txt
poetry_windows_fix-1.1.11.dist-info/LICENSE
poetry_windows_fix-1.1.11.dist-info/WHEEL
poetry_windows_fix-1.1.11.dist-info/METADATA
poetry_windows_fix-1.1.11.dist-info/RECORD
