Metadata-Version: 2.1
Name: poetry-windows-fix
Version: 1.1.11
Summary: A fix for Poetry; Python dependency management and packaging made easy.
Home-page: https://python-poetry.org/
License: MIT
Keywords: packaging,dependency,poetry
Author: Daan Luttik
Author-email: dtluttik@gmail.com
Requires-Python: >=2.7, !=3.0.*, !=3.1.*, !=3.2.*, !=3.3.*, !=3.4.*
Classifier: License :: OSI Approved :: MIT License
Classifier: Programming Language :: Python :: 2
Classifier: Programming Language :: Python :: 2.7
Classifier: Programming Language :: Python :: 3
Classifier: Programming Language :: Python :: 3.10
Classifier: Programming Language :: Python :: 3.5
Classifier: Programming Language :: Python :: 3.6
Classifier: Programming Language :: Python :: 3.7
Classifier: Programming Language :: Python :: 3.8
Classifier: Programming Language :: Python :: 3.9
Classifier: Topic :: Software Development :: Build Tools
Classifier: Topic :: Software Development :: Libraries :: Python Modules
Requires-Dist: cachecontrol[filecache] (>=0.12.4,<0.13.0)
Requires-Dist: cachy (>=0.3.0,<0.4.0)
Requires-Dist: cleo (>=0.8.1,<0.9.0)
Requires-Dist: clikit (>=0.6.2,<0.7.0)
Requires-Dist: crashtest (>=0.3.0,<0.4.0); python_version >= "3.6" and python_version < "4.0"
Requires-Dist: functools32 (>=3.2.3,<4.0.0); python_version >= "2.7" and python_version < "2.8"
Requires-Dist: futures (>=3.3.0,<4.0.0); python_version >= "2.7" and python_version < "2.8"
Requires-Dist: glob2 (>=0.6,<0.7); python_version >= "2.7" and python_version < "2.8"
Requires-Dist: html5lib (>=1.0,<2.0)
Requires-Dist: importlib-metadata (>=1.6.0,<2.0.0); python_version < "3.8"
Requires-Dist: keyring (>=18.0.1,<19.0.0); python_version >= "2.7" and python_version < "2.8"
Requires-Dist: keyring (>=20.0.1,<21.0.0); python_version >= "3.5" and python_version < "3.6"
Requires-Dist: keyring (>=21.2.0,<22.0.0); python_version >= "3.6" and python_version < "4.0"
Requires-Dist: packaging (>=20.4,<21.0)
Requires-Dist: pathlib2 (>=2.3,<3.0); python_version >= "2.7" and python_version < "2.8"
Requires-Dist: pexpect (>=4.7.0,<5.0.0)
Requires-Dist: pkginfo (>=1.4,<2.0)
Requires-Dist: poetry-core (>=1.0.7,<1.1.0)
Requires-Dist: requests (>=2.18,<3.0)
Requires-Dist: requests-toolbelt (>=0.9.1,<0.10.0)
Requires-Dist: shellingham (>=1.1,<2.0)
Requires-Dist: subprocess32 (>=3.5,<4.0); python_version >= "2.7" and python_version < "2.8"
Requires-Dist: tomlkit (>=0.7.0,<1.0.0)
Requires-Dist: typing (>=3.6,<4.0); python_version >= "2.7" and python_version < "2.8"
Requires-Dist: virtualenv (>=20.0.26,<21.0.0)
Project-URL: Documentation, https://python-poetry.org/docs
Project-URL: Repository, https://github.com/python-poetry/poetry
